{"chunk_definitions":[{"row":33,"row_count":1,"visible":true,"expansion_state":0,"options":{"engine":"r","label":"setup","include":false},"document_id":"CAFC7B04","chunk_id":"csetup_chunk","chunk_label":"setup"},{"row":44,"row_count":1,"visible":true,"expansion_state":0,"options":{"engine":"r","label":"unnamed-chunk-62"},"document_id":"CAFC7B04","chunk_id":"cz9uyb7o2cv0a","chunk_label":"unnamed-chunk-1"},{"row":50,"row_count":1,"visible":true,"expansion_state":0,"options":{"engine":"r","label":"unnamed-chunk-63"},"document_id":"CAFC7B04","chunk_id":"cr2j8lgxtypnr","chunk_label":"unnamed-chunk-2"},{"row":67,"row_count":1,"visible":true,"expansion_state":0,"options":{"engine":"r","label":"unnamed-chunk-64"},"document_id":"CAFC7B04","chunk_id":"cw3kh4397hzz0","chunk_label":"unnamed-chunk-3"},{"row":78,"row_count":1,"visible":true,"expansion_state":0,"options":{"engine":"r","label":"unnamed-chunk-65"},"document_id":"CAFC7B04","chunk_id":"cfl9q1sl7kdjl","chunk_label":"unnamed-chunk-4"},{"row":100,"row_count":1,"visible":true,"expansion_state":0,"options":{"engine":"r","label":"unnamed-chunk-71"},"document_id":"CAFC7B04","chunk_id":"cixo0ya5ghc27","chunk_label":"unnamed-chunk-5"},{"row":116,"row_count":1,"visible":true,"expansion_state":0,"options":{"engine":"r","label":"unnamed-chunk-72"},"document_id":"CAFC7B04","chunk_id":"c2z0x0v24urbb","chunk_label":"unnamed-chunk-6"},{"row":127,"row_count":1,"visible":true,"expansion_state":0,"options":{"engine":"r","label":"unnamed-chunk-73"},"document_id":"CAFC7B04","chunk_id":"cg2o2qxcgp3cs","chunk_label":"unnamed-chunk-7"},{"row":138,"row_count":1,"visible":true,"expansion_state":0,"options":{"engine":"r","label":"unnamed-chunk-58"},"document_id":"CAFC7B04","chunk_id":"cb3h853xrcf3w","chunk_label":"unnamed-chunk-8"},{"row":144,"row_count":1,"visible":true,"expansion_state":0,"options":{"engine":"r","label":"unnamed-chunk-59"},"document_id":"CAFC7B04","chunk_id":"cqspptn3a42hi","chunk_label":"unnamed-chunk-9"},{"row":161,"row_count":1,"visible":true,"expansion_state":0,"options":{"engine":"r","label":"unnamed-chunk-60"},"document_id":"CAFC7B04","chunk_id":"c59semuvui7hj","chunk_label":"unnamed-chunk-10"},{"row":172,"row_count":1,"visible":true,"expansion_state":0,"options":{"engine":"r","label":"unnamed-chunk-61"},"document_id":"CAFC7B04","chunk_id":"c8treakojxx7s","chunk_label":"unnamed-chunk-11"}],"doc_write_time":1615317458,"working_dir":null,"chunk_rendered_width":521}